.gitignore
LICENSE
README.rst
setup.cfg
setup.py
pyramid_cli/__about__.py
pyramid_cli/__init__.py
pyramid_cli.egg-info/PKG-INFO
pyramid_cli.egg-info/SOURCES.txt
pyramid_cli.egg-info/dependency_links.txt
pyramid_cli.egg-info/entry_points.txt
pyramid_cli.egg-info/requires.txt
pyramid_cli.egg-info/top_level.txt
pyramid_cli.egg-info/zip-safe
pyramid_cli/cli/__init__.py
pyramid_cli/cli/routes.py
pyramid_cli/cli/serve.py
pyramid_cli/cli/shell.py
pyramid_cli/config/__init__.py
pyramid_cli/config/yaml.py
requirements/install.txt
requirements/test.txt
tests/config/test_yaml.py
tests/fixtures/app.yaml
tests/fixtures/bad_env_var_directive.yaml
tests/fixtures/bad_include.yaml
tests/fixtures/env_vars.yaml
tests/fixtures/logging.yaml
tests/fixtures/server.yaml