Metadata-Version: 1.1
Name: pyramid-cli
Version: 0.0.2
Summary: Tools for managing pyramid applications!
Home-page: http://github.com/surveymonkey/pyramid_cli
Author: John Anderson
Author-email: johna@surveymonkey.com
License: MIT
Platform: UNKNOWN
Classifier: Development Status :: 5 - Production/Stable
Classifier: Intended Audience :: Developers
Classifier: License :: OSI Approved :: MIT License
Classifier: Programming Language :: Python :: 3
Classifier: Programming Language :: Python :: 3.4
